pyarch/__init__.py
pyarch/combinational/__init__.py
pyarch/combinational/arithmetics.py
pyarch/combinational/decoders.py
pyarch/combinational/gates.py
pyarch/connectors/__init__.py
pyarch/connectors/transport.py
pyarch/samples/__init__.py
pyarch/samples/plug-in-2x4Decoder.py
pyarch/samples/plug-in-GrayCode.py
pyarch/samples/plug-in-PipoAdder.py
pyarch/samples/plug-in-SRff.py
pyarch/samples/plug-in-and.py
pyarch/samples/plug-in-fulladder.py
pyarch/sequential/__init__.py
pyarch/sequential/ff.py
pyarch/utils/__init__.py
pyarch/utils/ioManager.py
pyarch/utils/new.py
pyarch-0.0.4.dist-info/DESCRIPTION.rst
pyarch-0.0.4.dist-info/METADATA
pyarch-0.0.4.dist-info/RECORD
pyarch-0.0.4.dist-info/WHEEL
pyarch-0.0.4.dist-info/metadata.json
pyarch-0.0.4.dist-info/top_level.txt
