Metadata-Version: 2.0
Name: pyarch
Version: 0.0.4
Summary: Hardware emulation library in python
Home-page: https://github.com/jumpip/PyArch
Author: Prachi Manchanda
Author-email: prachi121096@gmail.com
License: MIT
Platform: UNKNOWN
Classifier: Development Status :: 3 - Alpha
Classifier: License :: OSI Approved :: MIT License
Classifier: Programming Language :: Python :: 2
Classifier: Programming Language :: Python :: 2.6
Classifier: Programming Language :: Python :: 2.7
Requires-Dist: hiatus
Requires-Dist: pyee
